__init__.py
amoeba/__init__.py
amoeba/Classes/__init__.py
amoeba/Classes/accretion_disk.py
amoeba/Classes/agn.py
amoeba/Classes/blr.py
amoeba/Classes/blr_streamline.py
amoeba/Classes/diffuse_continuum.py
amoeba/Classes/flux_projection.py
amoeba/Classes/magnification_map.py
amoeba/Classes/torus.py
amoeba/Util/__init__.py
amoeba/Util/pipeline_util.py
amoeba/Util/util.py
amoeba_agn-0.2.2.dist-info/licenses/AUTHORS.rst
amoeba_agn-0.2.2.dist-info/licenses/LICENSE
amoeba_agn-0.2.2.dist-info/METADATA
amoeba_agn-0.2.2.dist-info/WHEEL
amoeba_agn-0.2.2.dist-info/top_level.txt
amoeba_agn-0.2.2.dist-info/RECORD
