Metadata-Version: 2.4
Name: amoeba-agn
Version: 0.2.2
Summary: This package is designed to model agn variability self consistently across multiple models
Author-email: Henry James Best V <hbest@gradcenter.cuny.edu>
Maintainer-email: Henry James Best V <hbest@gradcenter.cuny.edu>
License: MIT license
Project-URL: bugs, https://github.com/Henry-Best-01/amoeba/issues
Project-URL: changelog, https://github.com/Henry-Best-01/amoeba/blob/master/changelog.md
Project-URL: homepage, https://github.com/Henry-Best-01/amoeba
Classifier: Development Status :: 4 - Beta
Classifier: License :: OSI Approved :: MIT License
Classifier: Natural Language :: English
Classifier: Programming Language :: Python :: 3
License-File: LICENSE
License-File: AUTHORS.rst
Requires-Dist: astropy
Requires-Dist: numpy
Requires-Dist: scipy
Requires-Dist: scikit-image
Requires-Dist: speclite
Requires-Dist: tqdm
Requires-Dist: matplotlib
Provides-Extra: dev
Requires-Dist: coverage; extra == "dev"
Requires-Dist: mypy; extra == "dev"
Requires-Dist: pytest; extra == "dev"
Requires-Dist: ruff; extra == "dev"
Dynamic: license-file
